README.rst
setup.py
hse_ruz.egg-info/PKG-INFO
hse_ruz.egg-info/SOURCES.txt
hse_ruz.egg-info/dependency_links.txt
hse_ruz.egg-info/top_level.txt
ruz/__init__.py
ruz/api.py
ruz/schema.py
ruz/utils.py